README.rst
setup.py
pytsmp/__init__.py
pytsmp/pytsmp.py
pytsmp/utils.py
pytsmp.egg-info/PKG-INFO
pytsmp.egg-info/SOURCES.txt
pytsmp.egg-info/dependency_links.txt
pytsmp.egg-info/requires.txt
pytsmp.egg-info/top_level.txt