Metadata-Version: 1.1
Name: pytsmp
Version: 0.3.0
Summary: A Python implementation of the matrix profile
Home-page: https://github.com/kithomak/pytsmp
Author: Kit-Ho Mak
Author-email: kithomak23@gmail.com
License: MIT
Platform: UNKNOWN
Classifier: Development Status :: 2 - Pre-Alpha
Classifier: License :: OSI Approved :: MIT License
Classifier: Programming Language :: Python
Classifier: Programming Language :: Python :: 3
Classifier: Programming Language :: Python :: 3.4
Classifier: Programming Language :: Python :: 3.5
Classifier: Programming Language :: Python :: 3.6
Classifier: Programming Language :: Python :: 3.7
